woptics/__init__.py
woptics/fibre.py
woptics/tests/__init__.py
woptics/tests/test_fibre.py
woptics-0.0.1.dist-info/LICENSE.md
woptics-0.0.1.dist-info/METADATA
woptics-0.0.1.dist-info/WHEEL
woptics-0.0.1.dist-info/top_level.txt
woptics-0.0.1.dist-info/RECORD
