Metadata-Version: 2.1
Name: woptics
Version: 0.0.1
Summary: Light propogation simluation, using the scalar wave propogation approximation
Home-page: https://github.com/rjkilpatrick/woptics
Author: John Kilpatrick
Author-email: john.kilpatrick@outlook.com
License: MIT
Platform: UNKNOWN
Classifier: Development Status :: 1 - Planning
Classifier: Topic :: Scientific/Engineering
Classifier: Topic :: Scientific/Engineering :: Physics
Classifier: License :: OSI Approved :: MIT License
Classifier: Programming Language :: Python
Classifier: Programming Language :: Python :: 3
Classifier: Intended Audience :: Science/Research
Requires-Python: >=3.4
Requires-Dist: numpy
Requires-Dist: matplotlib
Requires-Dist: scipy
